Metadata-Version: 1.1
Name: django-superform
Version: 0.3.0
Summary: So much easier handling of formsets.
Home-page: https://github.com/gregmuellegger/django-superform
Author: Gregor Müllegger
Author-email: gregor@muellegger.de
License: BSD licence, see LICENSE file
Platform: UNKNOWN
Classifier: Development Status :: 3 - Alpha
Classifier: Environment :: Web Environment
Classifier: Framework :: Django
Classifier: Intended Audience :: Developers
Classifier: License :: OSI Approved :: BSD License
Classifier: Natural Language :: English
Classifier: Programming Language :: Python
Classifier: Programming Language :: Python :: 2
Classifier: Programming Language :: Python :: 2.6
Classifier: Programming Language :: Python :: 2.7
Classifier: Programming Language :: Python :: 3
Classifier: Programming Language :: Python :: 3.3
Classifier: Programming Language :: Python :: 3.4
